[
  {
    "ContainingType": "LibraryWebApi.Controllers.AccountController",
    "Method": "AddUser",
    "RelativePath": "api/Account/AddUser",
    "HttpMethod": "POST",
    "IsController": true,
    "Order": 0,
    "Parameters": [
      {
        "Name": "addUserDto",
        "Type": "Application.Layer.DTOs.AddUserDto",
        "IsRequired": true
      }
    ],
    "ReturnTypes": []
  },
  {
    "ContainingType": "LibraryWebApi.Controllers.AccountController",
    "Method": "Login",
    "RelativePath": "api/Account/Login",
    "HttpMethod": "POST",
    "IsController": true,
    "Order": 0,
    "Parameters": [
      {
        "Name": "loginDto",
        "Type": "Application.Layer.DTOs.LoginDto",
        "IsRequired": true
      }
    ],
    "ReturnTypes": []
  },
  {
    "ContainingType": "LibraryWebApi.Controllers.BookController",
    "Method": "AddBook",
    "RelativePath": "api/Book/AddBook",
    "HttpMethod": "POST",
    "IsController": true,
    "Order": 0,
    "Parameters": [
      {
        "Name": "book",
        "Type": "Application.Layer.DTOs.AddBookDto",
        "IsRequired": true
      }
    ],
    "ReturnTypes": []
  },
  {
    "ContainingType": "LibraryWebApi.Controllers.BookController",
    "Method": "GetAllBooks",
    "RelativePath": "api/Book/GetAllBooks",
    "HttpMethod": "GET",
    "IsController": true,
    "Order": 0,
    "Parameters": [],
    "ReturnTypes": []
  }
]